rexify/__init__.py
rexify/data/__init__.py
rexify/data/base.py
rexify/data/input.py
rexify/data/output.py
rexify/features/__init__.py
rexify/features/base.py
rexify/features/extractor.py
rexify/features/transform/__init__.py
rexify/features/transform/category.py
rexify/features/transform/custom.py
rexify/features/transform/entity.py
rexify/features/transform/event.py
rexify/features/transform/id.py
rexify/features/transform/number.py
rexify/features/transform/sequence.py
rexify/models/__init__.py
rexify/models/base.py
rexify/models/callbacks/__init__.py
rexify/models/callbacks/index.py
rexify/models/callbacks/mlflow.py
rexify/models/index.py
rexify/models/lookup.py
rexify/models/ranking/__init__.py
rexify/models/ranking/base.py
rexify/models/ranking/event.py
rexify/models/ranking/ranking.py
rexify/models/recommender.py
rexify/models/retrieval/__init__.py
rexify/models/retrieval/candidate.py
rexify/models/retrieval/query.py
rexify/models/retrieval/retrieval.py
rexify/models/retrieval/tower.py
rexify/models/sequential.py
rexify/pipeline/__init__.py
rexify/pipeline/__main__.py
rexify/pipeline/components/__init__.py
rexify/pipeline/components/load.py
rexify/pipeline/components/train.py
rexify/schema.py
rexify/utils.py
rexify-0.1.21.dist-info/LICENSE
rexify-0.1.21.dist-info/METADATA
rexify-0.1.21.dist-info/WHEEL
rexify-0.1.21.dist-info/RECORD
