Metadata-Version: 2.1
Name: rexify
Version: 0.1.21
Summary: Streamlined Recommender System workflows with TensorFlow and Kubeflow
License: MIT
Author: José Medeiros
Author-email: joseprsm@gmail.com
Requires-Python: >=3.8,<3.11
Classifier: Development Status :: 3 - Alpha
Classifier: Intended Audience :: Developers
Classifier: Intended Audience :: Information Technology
Classifier: License :: OSI Approved :: MIT License
Classifier: Operating System :: OS Independent
Classifier: Programming Language :: Python :: 3
Classifier: Programming Language :: Python :: 3.8
Classifier: Programming Language :: Python :: 3.9
Classifier: Programming Language :: Python :: 3.10
Classifier: Programming Language :: Python :: 3 :: Only
Classifier: Programming Language :: Python :: 3.10
Classifier: Programming Language :: Python :: 3.8
Classifier: Programming Language :: Python :: 3.9
Classifier: Topic :: Scientific/Engineering :: Artificial Intelligence
Classifier: Topic :: Software Development
Classifier: Topic :: Software Development :: Libraries
Classifier: Topic :: Software Development :: Libraries :: Python Modules
Provides-Extra: kfp
Provides-Extra: mlflow
Provides-Extra: scann
Requires-Dist: fsspec (==2023.4.0) ; extra == "kfp"
Requires-Dist: kfp (>=1.8.0,<2.0.0) ; extra == "kfp"
Requires-Dist: mlflow (>=2.3.0,<3.0.0) ; extra == "mlflow"
Requires-Dist: numpy (>=1.22.3)
Requires-Dist: pandas (>=1.4.0,<2.0.0)
Requires-Dist: scann (>=1.2.3,<2.0.0) ; (sys_platform != "darwin") and (extra == "scann")
Requires-Dist: scikit-learn (>=1.0.0,<2.0.0)
Requires-Dist: tensorflow (==2.9.0) ; sys_platform != "darwin"
Requires-Dist: tensorflow_macos (==2.9.0) ; sys_platform == "darwin"
Requires-Dist: tensorflow_metal (==0.5.0) ; sys_platform == "darwin"
Requires-Dist: tensorflow_recommenders (>=0.7.2)
Project-URL: Documentation, https://rexify.readthedocs.io
